MANIFEST.in
README.md
setup.cfg
setup.py
dublintraceroute/__init__.py
dublintraceroute/__main__.py
dublintraceroute/dublintraceroute.py
dublintraceroute/tracerouteresults.py
dublintraceroute.egg-info/PKG-INFO
dublintraceroute.egg-info/SOURCES.txt
dublintraceroute.egg-info/dependency_links.txt
dublintraceroute.egg-info/top_level.txt
dublintraceroute/py2/_dublintraceroute.cc
dublintraceroute/py3/_dublintraceroute.cc