Metadata-Version: 1.1
Name: dublintraceroute
Version: 0.4.2
Summary: NAT-aware multipath traceroute
Home-page: https://www.dublin-traceroute.net
Author: Andrea Barberio
Author-email: insomniac@slackware.it
License: BSD
Download-URL: https://github.com/insomniacslk/python-dublin-traceroute/archive/v0.4.0.tar.gz
Keywords: traceroute,networking,multipath,nat
Platform: linux
Platform: darwin
